[
    {
        "601": 603,
        "44562": 44562,
        "general_de_ley_personas_morales": "Personas Morales con Fines no Lucrativos",
        "no": "No",
        "si": "Sí"
    },
    {
        "601": 605,
        "44562": 44562,
        "general_de_ley_personas_morales": "Sueldos y Salarios e Ingresos Asimilados a Salarios",
        "no": "Sí",
        "si": "No"
    },
    {
        "601": 606,
        "44562": 44562,
        "general_de_ley_personas_morales": "Arrendamiento",
        "no": "Sí",
        "si": "No"
    },
    {
        "601": 607,
        "44562": 44562,
        "general_de_ley_personas_morales": "Régimen de Enajenación o Adquisición de Bienes",
        "no": "Sí",
        "si": "No"
    },
    {
        "601": 608,
        "44562": 44562,
        "general_de_ley_personas_morales": "Demás ingresos",
        "no": "Sí",
        "si": "No"
    },
    {
        "601": 610,
        "44562": 44562,
        "general_de_ley_personas_morales": "Residentes en el Extranjero sin Establecimiento Permanente en México",
        "no": "Sí",
        "si": "Sí"
    },
    {
        "601": 611,
        "44562": 44562,
        "general_de_ley_personas_morales": "Ingresos por Dividendos (socios y accionistas)",
        "no": "Sí",
        "si": "No"
    },
    {
        "601": 612,
        "44562": 44562,
        "general_de_ley_personas_morales": "Personas Físicas con Actividades Empresariales y Profesionales",
        "no": "Sí",
        "si": "No"
    },
    {
        "601": 614,
        "44562": 44562,
        "general_de_ley_personas_morales": "Ingresos por intereses",
        "no": "Sí",
        "si": "No"
    },
    {
        "601": 615,
        "44562": 44562,
        "general_de_ley_personas_morales": "Régimen de los ingresos por obtención de premios",
        "no": "Sí",
        "si": "No"
    },
    {
        "601": 616,
        "44562": 44562,
        "general_de_ley_personas_morales": "Sin obligaciones fiscales",
        "no": "Sí",
        "si": "No"
    },
    {
        "601": 620,
        "44562": 44562,
        "general_de_ley_personas_morales": "Sociedades Cooperativas de Producción que optan por diferir sus ingresos",
        "no": "No",
        "si": "Sí"
    },
    {
        "601": 621,
        "44562": 44562,
        "general_de_ley_personas_morales": "Incorporación Fiscal",
        "no": "Sí",
        "si": "No"
    },
    {
        "601": 622,
        "44562": 44562,
        "general_de_ley_personas_morales": "Actividades Agrícolas, Ganaderas, Silvícolas y Pesqueras",
        "no": "No",
        "si": "Sí"
    },
    {
        "601": 623,
        "44562": 44562,
        "general_de_ley_personas_morales": "Opcional para Grupos de Sociedades",
        "no": "No",
        "si": "Sí"
    },
    {
        "601": 624,
        "44562": 44562,
        "general_de_ley_personas_morales": "Coordinados",
        "no": "No",
        "si": "Sí"
    },
    {
        "601": 625,
        "44562": 44562,
        "general_de_ley_personas_morales": "Régimen de las Actividades Empresariales con ingresos a través de Plataformas Tecnológicas",
        "no": "Sí",
        "si": "No"
    },
    {
        "601": 626,
        "44562": 44562,
        "general_de_ley_personas_morales": "Régimen Simplificado de Confianza",
        "no": "Sí",
        "si": "Sí"
    }
]